hydra/__init__.py
hydra/admin.py
hydra/apps.py
hydra/context_processors.py
hydra/decorators.py
hydra/forms.py
hydra/models.py
hydra/options.py
hydra/settings.py
hydra/shortcuts.py
hydra/signals.py
hydra/sites.py
hydra/tests.py
hydra/utils.py
hydra/management/__init__.py
hydra/management/commands/__init__.py
hydra/management/commands/createactions.py
hydra/management/commands/createbasemenu.py
hydra/management/commands/createpermission.py
hydra/migrations/0001_action_menu.py
hydra/migrations/__init__.py
hydra/migrations/unaccent_extension.py
hydra/mixins/__init__.py
hydra/mixins/breadcrumbs.py
hydra/mixins/filters.py
hydra/mixins/formsets.py
hydra/mixins/permissions.py
hydra/mixins/templates.py
hydra/mixins/urls.py
hydra/templatetags/__init__.py
hydra/templatetags/hydra.py
hydra/views/__init__.py
hydra/views/base.py
hydra/views/create.py
hydra/views/delete.py
hydra/views/detail.py
hydra/views/duplicate.py
hydra/views/list.py
hydra/views/update.py
django_hydra-0.9.9.dist-info/LICENCE
django_hydra-0.9.9.dist-info/METADATA
django_hydra-0.9.9.dist-info/WHEEL
django_hydra-0.9.9.dist-info/top_level.txt
django_hydra-0.9.9.dist-info/RECORD
